mermaid2/__init__.py
mermaid2/fence.py
mermaid2/plugin.py
mermaid2/pyjs.py
mermaid2/util.py
test/__init__.py
test/fixture.py
test/material/__init__.py
test/material/test_site.py
test/simple/__init__.py
test/simple/test_site.py
test/superfences/__init__.py
test/superfences/test_site.py
mkdocs_mermaid2_plugin-1.2.1.dist-info/LICENSE
mkdocs_mermaid2_plugin-1.2.1.dist-info/METADATA
mkdocs_mermaid2_plugin-1.2.1.dist-info/WHEEL
mkdocs_mermaid2_plugin-1.2.1.dist-info/entry_points.txt
mkdocs_mermaid2_plugin-1.2.1.dist-info/top_level.txt
mkdocs_mermaid2_plugin-1.2.1.dist-info/RECORD
