Metadata-Version: 2.1
Name: mkdocs-mermaid2-plugin
Version: 1.2.1
Summary: A MkDocs plugin for including mermaid graphs in markdown sources
Author: Laurent Franceschetti
License: MIT
Project-URL: Homepage, https://github.com/fralau/mkdocs-mermaid2-plugin
Keywords: markdown,mermaid,mkdocs,python
Classifier: Development Status :: 5 - Production/Stable
Classifier: Intended Audience :: Developers
Classifier: Intended Audience :: Information Technology
Classifier: License :: OSI Approved :: MIT License
Classifier: Programming Language :: Python :: 3
Classifier: Programming Language :: Python :: 3.5
Classifier: Programming Language :: Python :: 3.6
Classifier: Programming Language :: Python :: 3.7
Classifier: Programming Language :: Python :: 3.8
Requires-Python: >=3.8
License-File: LICENSE
Requires-Dist: beautifulsoup4>=4.6.3
Requires-Dist: jsbeautifier
Requires-Dist: mkdocs>=1.0.4
Requires-Dist: pymdown-extensions>=8.0
Requires-Dist: requests
Requires-Dist: setuptools>=18.5
Provides-Extra: test
Requires-Dist: mkdocs-macros-test; extra == "test"
Requires-Dist: mkdocs-material; extra == "test"
Requires-Dist: packaging; extra == "test"
Requires-Dist: requests-html; extra == "test"
